fastpluggy_official_plugins/__init__.py
fastpluggy_official_plugins/bootstrap.py
fastpluggy_official_plugins/plugins/crud_tools/__init__.py
fastpluggy_official_plugins/plugins/crud_tools/config.py
fastpluggy_official_plugins/plugins/crud_tools/crud_admin.py
fastpluggy_official_plugins/plugins/crud_tools/crud_admin_registry.py
fastpluggy_official_plugins/plugins/crud_tools/crud_link_helper.py
fastpluggy_official_plugins/plugins/crud_tools/menu_tools.py
fastpluggy_official_plugins/plugins/crud_tools/plugin.py
fastpluggy_official_plugins/plugins/crud_tools/requirements.txt
fastpluggy_official_plugins/plugins/crud_tools/schema.py
fastpluggy_official_plugins/plugins/crud_tools/template_tools.py
fastpluggy_official_plugins/plugins/crud_tools/field_types/__init__.py
fastpluggy_official_plugins/plugins/crud_tools/field_types/date_fields.py
fastpluggy_official_plugins/plugins/crud_tools/field_types/dynamic_fields.py
fastpluggy_official_plugins/plugins/crud_tools/field_types/entity_fields.py
fastpluggy_official_plugins/plugins/crud_tools/field_types/enum_fields.py
fastpluggy_official_plugins/plugins/crud_tools/field_types/timedelta_fields.py
fastpluggy_official_plugins/plugins/crud_tools/router/__init__.py
fastpluggy_official_plugins/plugins/crud_tools/router/api.py
fastpluggy_official_plugins/plugins/crud_tools/router/crud.py
fastpluggy_official_plugins/plugins/crud_tools/router/crud_admin.py
fastpluggy_official_plugins/plugins/crud_tools/static/js/dynamic-select.js
fastpluggy_official_plugins/plugins/crud_tools/tests/test_link_helper.py
fastpluggy_official_plugins/plugins/redis_tools/README.md
fastpluggy_official_plugins/plugins/redis_tools/__init__.py
fastpluggy_official_plugins/plugins/redis_tools/config.py
fastpluggy_official_plugins/plugins/redis_tools/plugin.py
fastpluggy_official_plugins/plugins/redis_tools/redis_connector.py
fastpluggy_official_plugins/plugins/redis_tools/requirements.txt
fastpluggy_official_plugins/plugins/redis_tools/router.py
fastpluggy_official_plugins-0.1.23.dist-info/METADATA
fastpluggy_official_plugins-0.1.23.dist-info/WHEEL
fastpluggy_official_plugins-0.1.23.dist-info/top_level.txt
fastpluggy_official_plugins-0.1.23.dist-info/RECORD
