Metadata-Version: 2.4
Name: fastpluggy-official-plugins
Version: 0.1.23
Summary: Official plugin bundle for FastPluggy
Author-email: Your Name <you@example.com>
Requires-Python: >=3.10
